{"chunks": [{"number": "21", "title": "CSS Media Queries & Responsive Design", "start": 0.0, "end": 10.0, "text": " In this video, we will learn about CSS media queries and responsive web design."}, {"number": "21", "title": "CSS Media Queries & Responsive Design", "start": 10.0, "end": 20.0, "text": " Responsive web design means your website looks good on all devices."}, {"number": "21", "title": "CSS Media Queries & Responsive Design", "start": 20.0, "end": 30.0, "text": " It should look good on mobile phones, tablets, laptops, and desktop screens."}, {"number": "21", "title": "CSS Media Queries & Responsive Design", "start": 30.0, "end": 40.0, "text": " Media queries are the foundation of responsive web design in CSS."}, {"number": "21", "title": "CSS Media Queries & Responsive Design", "start": 40.0, "end": 50.0, "text": " A media query applies styles based on the result of one or more media expressions."}, {"number": "21", "title": "CSS Media Queries & Responsive Design", "start": 50.0, "end": 60.0, "text": " The basic syntax is @media screen and max-width 768px."}, {"number": "21", "title": "CSS Media Queries & Responsive Design", "start": 60.0, "end": 70.0, "text": " This means the styles inside will only apply when screen width is 768 pixels or less."}, {"number": "21", "title": "CSS Media Queries & Responsive Design", "start": 70.0, "end": 80.0, "text": " Common breakpoints are 576px for phones, 768px for tablets, 992px for laptops, 1200px for desktops."}, {"number": "21", "title": "CSS Media Queries & Responsive Design", "start": 80.0, "end": 90.0, "text": " Mobile-first design means you write styles for mobile first, then add media queries for larger screens."}, {"number": "21", "title": "CSS Media Queries & Responsive Design", "start": 90.0, "end": 100.0, "text": " Desktop-first design means you write styles for desktop first, then override for smaller screens."}, {"number": "21", "title": "CSS Media Queries & Responsive Design", "start": 100.0, "end": 110.0, "text": " Mobile-first is generally recommended as more people browse on mobile devices now."}, {"number": "21", "title": "CSS Media Queries & Responsive Design", "start": 110.0, "end": 120.0, "text": " The viewport meta tag is essential for responsive design to work on mobile devices."}, {"number": "21", "title": "CSS Media Queries & Responsive Design", "start": 120.0, "end": 130.0, "text": " Always add meta name viewport content width device-width initial-scale 1 in your HTML head."}, {"number": "21", "title": "CSS Media Queries & Responsive Design", "start": 130.0, "end": 140.0, "text": " You can also use media queries to change layout completely on different screen sizes."}, {"number": "21", "title": "CSS Media Queries & Responsive Design", "start": 140.0, "end": 150.0, "text": " For example, a sidebar layout on desktop can become a stacked layout on mobile."}, {"number": "21", "title": "CSS Media Queries & Responsive Design", "start": 150.0, "end": 160.0, "text": " The combination of Flexbox, Grid, and Media Queries gives you complete control over responsive layouts."}, {"number": "21", "title": "CSS Media Queries & Responsive Design", "start": 160.0, "end": 170.0, "text": " Let me show you a practical responsive design example from scratch."}, {"number": "21", "title": "CSS Media Queries & Responsive Design", "start": 170.0, "end": 180.0, "text": " We will create a responsive card layout that changes from 3 columns to 2 to 1."}, {"number": "21", "title": "CSS Media Queries & Responsive Design", "start": 180.0, "end": 190.0, "text": " Using CSS Grid with auto-fit and minmax, we can even avoid media queries for simple responsive grids."}, {"number": "21", "title": "CSS Media Queries & Responsive Design", "start": 190.0, "end": 200.0, "text": " Responsive design is not optional anymore, it is a requirement for every website."}, {"number": "21", "title": "CSS Media Queries & Responsive Design", "start": 200.0, "end": 210.0, "text": " Google also considers mobile-friendliness as a ranking factor in search results."}, {"number": "21", "title": "CSS Media Queries & Responsive Design", "start": 210.0, "end": 220.0, "text": " Always test your website on different screen sizes before deploying."}, {"number": "21", "title": "CSS Media Queries & Responsive Design", "start": 220.0, "end": 230.0, "text": " Browser DevTools have a device toolbar that lets you simulate different screen sizes."}, {"number": "21", "title": "CSS Media Queries & Responsive Design", "start": 230.0, "end": 240.0, "text": " In the next video, we will start learning JavaScript which is the programming language of the web."}], "text": "In this video, we will learn about CSS media queries and responsive web design. Responsive web design means your website looks good on all devices. It should look good on mobile phones, tablets, laptops, and desktop screens. Media queries are the foundation of responsive web design in CSS. A media query applies styles based on the result of one or more media expressions. The basic syntax is @media screen and max-width 768px. This means the styles inside will only apply when screen width is 768 pixels or less. Common breakpoints are 576px for phones, 768px for tablets, 992px for laptops, 1200px for desktops. Mobile-first design means you write styles for mobile first, then add media queries for larger screens. Desktop-first design means you write styles for desktop first, then override for smaller screens. Mobile-first is generally recommended as more people browse on mobile devices now. The viewport meta tag is essential for responsive design to work on mobile devices. Always add meta name viewport content width device-width initial-scale 1 in your HTML head. You can also use media queries to change layout completely on different screen sizes. For example, a sidebar layout on desktop can become a stacked layout on mobile. The combination of Flexbox, Grid, and Media Queries gives you complete control over responsive layouts. Let me show you a practical responsive design example from scratch. We will create a responsive card layout that changes from 3 columns to 2 to 1. Using CSS Grid with auto-fit and minmax, we can even avoid media queries for simple responsive grids. Responsive design is not optional anymore, it is a requirement for every website. Google also considers mobile-friendliness as a ranking factor in search results. Always test your website on different screen sizes before deploying. Browser DevTools have a device toolbar that lets you simulate different screen sizes. In the next video, we will start learning JavaScript which is the programming language of the web."}