{"chunks": [{"number": "29", "title": "JavaScript Functions & Arrow Functions", "start": 0.0, "end": 10.0, "text": " Functions are one of the fundamental building blocks in JavaScript."}, {"number": "29", "title": "JavaScript Functions & Arrow Functions", "start": 10.0, "end": 20.0, "text": " A function is a block of code designed to perform a particular task."}, {"number": "29", "title": "JavaScript Functions & Arrow Functions", "start": 20.0, "end": 30.0, "text": " You define a function using the function keyword followed by a name and parentheses."}, {"number": "29", "title": "JavaScript Functions & Arrow Functions", "start": 30.0, "end": 40.0, "text": " Parameters are listed inside the parentheses in the function definition."}, {"number": "29", "title": "JavaScript Functions & Arrow Functions", "start": 40.0, "end": 50.0, "text": " Arguments are the values passed to the function when it is invoked."}, {"number": "29", "title": "JavaScript Functions & Arrow Functions", "start": 50.0, "end": 60.0, "text": " The return statement stops the execution of a function and returns a value."}, {"number": "29", "title": "JavaScript Functions & Arrow Functions", "start": 60.0, "end": 70.0, "text": " A function without a return statement returns undefined."}, {"number": "29", "title": "JavaScript Functions & Arrow Functions", "start": 70.0, "end": 80.0, "text": " Function expressions assign a function to a variable."}, {"number": "29", "title": "JavaScript Functions & Arrow Functions", "start": 80.0, "end": 90.0, "text": " Arrow functions are a shorter syntax for writing function expressions."}, {"number": "29", "title": "JavaScript Functions & Arrow Functions", "start": 90.0, "end": 100.0, "text": " Arrow functions use the fat arrow syntax: const add equals parentheses arrow."}, {"number": "29", "title": "JavaScript Functions & Arrow Functions", "start": 100.0, "end": 110.0, "text": " If the function has only one expression, you can omit the curly braces and return keyword."}, {"number": "29", "title": "JavaScript Functions & Arrow Functions", "start": 110.0, "end": 120.0, "text": " Arrow functions do not have their own this keyword, which is important for objects."}, {"number": "29", "title": "JavaScript Functions & Arrow Functions", "start": 120.0, "end": 130.0, "text": " Default parameters allow you to set default values for function parameters."}, {"number": "29", "title": "JavaScript Functions & Arrow Functions", "start": 130.0, "end": 140.0, "text": " Rest parameters allow a function to accept an indefinite number of arguments as an array."}, {"number": "29", "title": "JavaScript Functions & Arrow Functions", "start": 140.0, "end": 150.0, "text": " Callback functions are functions passed as arguments to other functions."}, {"number": "29", "title": "JavaScript Functions & Arrow Functions", "start": 150.0, "end": 160.0, "text": " Callbacks are heavily used in JavaScript for asynchronous operations."}, {"number": "29", "title": "JavaScript Functions & Arrow Functions", "start": 160.0, "end": 170.0, "text": " Higher-order functions are functions that take other functions as arguments or return functions."}, {"number": "29", "title": "JavaScript Functions & Arrow Functions", "start": 170.0, "end": 180.0, "text": " Map, filter, and reduce are examples of higher-order functions."}, {"number": "29", "title": "JavaScript Functions & Arrow Functions", "start": 180.0, "end": 190.0, "text": " IIFE stands for Immediately Invoked Function Expression. It runs as soon as it is defined."}, {"number": "29", "title": "JavaScript Functions & Arrow Functions", "start": 190.0, "end": 200.0, "text": " Closures are functions that have access to variables from their outer scope even after the outer function has returned."}, {"number": "29", "title": "JavaScript Functions & Arrow Functions", "start": 200.0, "end": 210.0, "text": " Understanding closures is very important for advanced JavaScript programming."}, {"number": "29", "title": "JavaScript Functions & Arrow Functions", "start": 210.0, "end": 220.0, "text": " Functions are first-class citizens in JavaScript, meaning they can be treated like any other value."}, {"number": "29", "title": "JavaScript Functions & Arrow Functions", "start": 220.0, "end": 230.0, "text": " Practice writing functions as they are the backbone of any JavaScript application."}], "text": "Functions are one of the fundamental building blocks in JavaScript. A function is a block of code designed to perform a particular task. You define a function using the function keyword followed by a name and parentheses. Parameters are listed inside the parentheses in the function definition. Arguments are the values passed to the function when it is invoked. The return statement stops the execution of a function and returns a value. A function without a return statement returns undefined. Function expressions assign a function to a variable. Arrow functions are a shorter syntax for writing function expressions. Arrow functions use the fat arrow syntax: const add equals parentheses arrow. If the function has only one expression, you can omit the curly braces and return keyword. Arrow functions do not have their own this keyword, which is important for objects. Default parameters allow you to set default values for function parameters. Rest parameters allow a function to accept an indefinite number of arguments as an array. Callback functions are functions passed as arguments to other functions. Callbacks are heavily used in JavaScript for asynchronous operations. Higher-order functions are functions that take other functions as arguments or return functions. Map, filter, and reduce are examples of higher-order functions. IIFE stands for Immediately Invoked Function Expression. It runs as soon as it is defined. Closures are functions that have access to variables from their outer scope even after the outer function has returned. Understanding closures is very important for advanced JavaScript programming. Functions are first-class citizens in JavaScript, meaning they can be treated like any other value. Practice writing functions as they are the backbone of any JavaScript application."}